pandoc_code_attribute.py
pandoc_code_attribute-0.2.0.dist-info/LICENSE
pandoc_code_attribute-0.2.0.dist-info/METADATA
pandoc_code_attribute-0.2.0.dist-info/WHEEL
pandoc_code_attribute-0.2.0.dist-info/entry_points.txt
pandoc_code_attribute-0.2.0.dist-info/top_level.txt
pandoc_code_attribute-0.2.0.dist-info/RECORD
