Metadata-Version: 2.1
Name: pandoc-code-attribute
Version: 0.2.0
Summary: Pandoc filter to add attributes to code blocks based on their classes
Home-page: https://github.com/DCsunset/pandoc-code-attribute
Author: DCsunset
Author-email: DCsunset@protonmail.com
License: MIT
Platform: UNKNOWN
Classifier: Environment :: Console
Classifier: Intended Audience :: End Users/Desktop
Classifier: Programming Language :: Python
Classifier: License :: OSI Approved :: MIT License
Requires-Dist: panflute (>=1)
